CHANGES.txt
LICENSE.txt
MANIFEST.in
README.txt
setup.py
logglyproxy/__init__.py
logglyproxy/keepalive.py
logglyproxy/server.py
logglyproxy.egg-info/PKG-INFO
logglyproxy.egg-info/SOURCES.txt
logglyproxy.egg-info/dependency_links.txt
logglyproxy.egg-info/entry_points.txt
logglyproxy.egg-info/requires.txt
logglyproxy.egg-info/top_level.txt