Metadata-Version: 1.0
Name: logglyproxy
Version: 1.0
Summary: A syslog proxy server forwarding messages to Loggly via HTTPS
Home-page: http://www.evax.fr/
Author: Evax Software
Author-email: contact@evax.fr
License: MIT License
Keywords: syslog,loggly,gevent,https
Platform: UNKNOWN
Classifier: Development Status :: 5 - Production/Stable
Classifier: Intended Audience :: System Administrators
Classifier: License :: OSI Approved :: MIT License
Classifier: Programming Language :: Python
Classifier: Operating System :: OS Independent
Classifier: Topic :: System :: Logging
Classifier: Topic :: Internet :: Log Analysis
